oastodcat/__init__.py
oastodcat/oas_dataservice.py
oastodcat-2.0.2.dist-info/LICENSE
oastodcat-2.0.2.dist-info/WHEEL
oastodcat-2.0.2.dist-info/METADATA
oastodcat-2.0.2.dist-info/RECORD
