Metadata-Version: 2.1
Name: oastodcat
Version: 2.0.2
Summary: A library for transforming an openAPI file to one or more dcat:DataService
Home-page: https://github.com/Informasjonsforvaltning/oastodcat
License: Apache-2.0
Author: Stig B. Dørmænen
Author-email: stigbd@gmail.com
Requires-Python: >=3.8,<3.11
Classifier: License :: OSI Approved :: Apache Software License
Classifier: Operating System :: OS Independent
Classifier: Programming Language :: Python :: 3
Classifier: Programming Language :: Python :: 3.10
Classifier: Programming Language :: Python :: 3.8
Classifier: Programming Language :: Python :: 3.9
Requires-Dist: PyYAML (>=6.0,<7.0)
Requires-Dist: datacatalogtordf (>=2.1.2,<3.0.0)
Requires-Dist: requests (>=2.24.0,<3.0.0)
Project-URL: Documentation, https://oastodcat.readthedocs.io
Project-URL: Repository, https://github.com/Informasjonsforvaltning/oastodcat
